MANIFEST.in
README.rst
setup.cfg
setup.py
docs/Makefile
docs/api_reference.rst
docs/conf.py
docs/developer_guide.rst
docs/index.rst
docs/make.bat
docs/quickstart_heroku.rst
docs/quickstart_ownserver.rst
docs/requirements.txt
docs/_static/.gitignore
docs/_templates/.gitignore
powerapp/__init__.py
powerapp/config.py
powerapp/database.py
powerapp/database_utils.py
powerapp/default_config.py
powerapp/eventloop.py
powerapp/exceptions.py
powerapp/init.py
powerapp/services.py
powerapp/utils.py
powerapp.egg-info/PKG-INFO
powerapp.egg-info/SOURCES.txt
powerapp.egg-info/dependency_links.txt
powerapp.egg-info/entry_points.txt
powerapp.egg-info/not-zip-safe
powerapp.egg-info/requires.txt
powerapp.egg-info/top_level.txt
powerapp/models/__init__.py
powerapp/models/integration_periodic_tasks.py
powerapp/models/integrations.py
powerapp/models/oauth_tokens.py
powerapp/models/todoist_users.py
powerapp/scripts/__init__.py
powerapp/scripts/cron.py
powerapp/scripts/eventloop.py
powerapp/scripts/shell.py
powerapp/scripts/webserver.py
powerapp/services_impl/__init__.py
powerapp/services_impl/amazon/__init__.py
powerapp/services_impl/amazon/controllers.py
powerapp/services_impl/amazon/service.py
powerapp/services_impl/rss/__init__.py
powerapp/services_impl/rss/controllers.py
powerapp/services_impl/rss/service.py
powerapp/web/__init__.py
powerapp/web/controllers.py
powerapp/web/forms.py
powerapp/web/oauth.py
powerapp/web/oauth_impl.py
powerapp/web/utils.py
powerapp/web/web.py
powerapp/web/static/default_logo.png
powerapp/web/static/powerapp.png
powerapp/web/static/powerapp150x150.png
powerapp/web/static/powerapp50x50.png
powerapp/web/static/css/bootstrap-theme.css
powerapp/web/static/css/bootstrap-theme.css.map
powerapp/web/static/css/bootstrap-theme.min.css
powerapp/web/static/css/bootstrap.css
powerapp/web/static/css/bootstrap.css.map
powerapp/web/static/css/bootstrap.min.css
powerapp/web/static/css/main.css
powerapp/web/static/fonts/glyphicons-halflings-regular.eot
powerapp/web/static/fonts/glyphicons-halflings-regular.svg
powerapp/web/static/fonts/glyphicons-halflings-regular.ttf
powerapp/web/static/fonts/glyphicons-halflings-regular.woff
powerapp/web/static/fonts/glyphicons-halflings-regular.woff2
