Metadata-Version: 1.1
Name: powerapp
Version: 0.1
Summary: The app to integrate Todoist with third-party services
Home-page: https://github.com/Doist/powerapp
Author: UNKNOWN
Author-email: UNKNOWN
License: BSD
Platform: UNKNOWN
Classifier: Development Status :: 3 - Alpha
Classifier: License :: OSI Approved :: BSD License
Classifier: Programming Language :: Python
Classifier: Programming Language :: Python :: 3
